xchainpy2_bsc/__init__.py
xchainpy2_bsc/bsc_client.py
xchainpy2_bsc/const.py
xchainpy2_bsc/data/bsc_mainnet_latest.json
xchainpy2_bsc-0.0.7.dist-info/LICENSE
xchainpy2_bsc-0.0.7.dist-info/METADATA
xchainpy2_bsc-0.0.7.dist-info/WHEEL
xchainpy2_bsc-0.0.7.dist-info/top_level.txt
xchainpy2_bsc-0.0.7.dist-info/RECORD
