Metadata-Version: 2.1
Name: xchainpy2_bsc
Version: 0.0.7
Summary: XChainPy2 Binance Smart Chain Client
Author-email: Tirinox <developer@tirinox.ru>
License: MIT
Project-URL: source, https://github.com/tirinox/xchainpy
Keywords: Crypto,BSC,BNB,BEP20,Smart chain,Binance,Blockchain,XChain
Classifier: Development Status :: 3 - Alpha
Classifier: Intended Audience :: Developers
Classifier: Topic :: Software Development :: Build Tools
Classifier: License :: OSI Approved :: MIT License
Classifier: Programming Language :: Python :: 3
Classifier: Programming Language :: Python :: 3.6
Classifier: Programming Language :: Python :: 3.7
Classifier: Programming Language :: Python :: 3.8
Classifier: Programming Language :: Python :: 3.9
Classifier: Programming Language :: Python :: 3.10
Classifier: Programming Language :: Python :: 3.11
Requires-Python: >=3.7
License-File: LICENSE
Requires-Dist: xchainpy2_utils
Requires-Dist: xchainpy2_crypto
Requires-Dist: xchainpy2_client
Requires-Dist: xchainpy2_ethereum
Provides-Extra: test
Requires-Dist: pytest; extra == "test"
